FrictionlessDarwinCore/__init__.py
FrictionlessDarwinCore/archive.py
FrictionlessDarwinCore/fdwc_terms.csv
FrictionlessDarwinCore/fdwca.py
FrictionlessDarwinCore/metadata.py
FrictionlessDarwinCore/resource.py
FrictionlessDarwinCore/structure.py
FrictionlessDarwinCore/vocabulary.py
FrictionlessDarwinCore/fdwc/fdwca/dwca/description.csv
FrictionlessDarwinCore/fdwc/fdwca/dwca/distribution.csv
FrictionlessDarwinCore/fdwc/fdwca/dwca/gbif-dwca.csv
FrictionlessDarwinCore/fdwc/fdwca/dwca/image.csv
FrictionlessDarwinCore/fdwc/fdwca/dwca/reference.csv
FrictionlessDarwinCore/fdwc/fdwca/dwca/specimen.csv
FrictionlessDarwinCore/fdwc/fdwca/dwca/vernacularnames.csv
FrictionlessDarwinCore-1.0.0.dist-info/LICENSE.md
FrictionlessDarwinCore-1.0.0.dist-info/METADATA
FrictionlessDarwinCore-1.0.0.dist-info/WHEEL
FrictionlessDarwinCore-1.0.0.dist-info/entry_points.txt
FrictionlessDarwinCore-1.0.0.dist-info/top_level.txt
FrictionlessDarwinCore-1.0.0.dist-info/RECORD
