Metadata-Version: 2.1
Name: FrictionlessDarwinCore
Version: 1.0.0
Summary: A tool converting Darwin Core Archive into Frictionless Data Package.
Home-page: UNKNOWN
Author: André Heughebaert
Author-email: andrejjh@gmail.com
License: MIT License
Platform: UNKNOWN
Classifier: Programming Language :: Python :: 3
Classifier: License :: OSI Approved :: MIT License
Classifier: Operating System :: OS Independent
Requires-Python: >=3.7
Requires-Dist: requests (==2.22.0)
Requires-Dist: Click (==7.0)
